orfmatch/__init__.py
orfmatch/main.py
orfmatch/plots.py
orfmatch-0.2.4.dist-info/METADATA
orfmatch-0.2.4.dist-info/WHEEL
orfmatch-0.2.4.dist-info/entry_points.txt
orfmatch-0.2.4.dist-info/licenses/LICENSE
orfmatch-0.2.4.dist-info/RECORD
