Metadata-Version: 2.4
Name: orfmatch
Version: 0.2.4
Summary: Transfer feature annotations from a reference genome to a de novo assembled one.
Project-URL: Homepage, https://github.com/mcgilmore/orfmatch
Project-URL: Repository, https://github.com/mcgilmore/orfmatch.git
Author-email: mcgilmore <michael_gilmore@live.com>
License-Expression: GPL-3.0-only
License-File: LICENSE
Requires-Python: >=3.9
Requires-Dist: biopython<2,>=1.85
Requires-Dist: pycirclize<2,>=1.9.1
Requires-Dist: pygenomeviz<2,>=1.6.1
Requires-Dist: pyhmmer<0.12,>=0.11.1
Requires-Dist: pyrodigal<4,>=3.6.3.post1
Requires-Dist: seaborn<0.14,>=0.13.2
Requires-Dist: tqdm<5,>=4.67.1
